<?xml version="1.0"?>
<results>
  <user>
    <user_id>7</user_id>
    <connect_id>100002210912688</connect_id>
    <username>george</username>
    <teamname>ND</teamname>
    <run>0</run>
  </user>
  <user>
    <user_id>160</user_id>
    <connect_id>100002716009748</connect_id>
    <username>DVSNath</username>
    <teamname>Atoms</teamname>
    <run>399</run>
  </user>
  <user>
    <user_id>323</user_id>
    <connect_id>100000360918575</connect_id>
    <username>indras</username>
    <teamname>indras</teamname>
    <run>522</run>
  </user>
  <user>
    <user_id>4</user_id>
    <connect_id>803015219</connect_id>
    <username>Tourettes</username>
    <teamname>danixycodes</teamname>
    <run>311</run>
  </user>
  <user>
    <user_id>834</user_id>
    <connect_id>100002190874289</connect_id>
    <username>sandeepchandran</username>
    <teamname>Sandy</teamname>
    <run>339</run>
  </user>
  <user>
    <user_id>5</user_id>
    <connect_id></connect_id>
    <username>karthik</username>
    <teamname>ND</teamname>
    <run>0</run>
  </user>
  <user>
    <user_id>280</user_id>
    <connect_id>100001378985686</connect_id>
    <username>harrisjose</username>
    <teamname>The Masters of Cricketers</teamname>
    <run>407</run>
  </user>
  <user>
    <user_id>355</user_id>
    <connect_id>100000781620629</connect_id>
    <username>Tendulkarz</username>
    <teamname>Tendulkarz</teamname>
    <run>608</run>
  </user>
  <user>
    <user_id>97</user_id>
    <connect_id>100002443011075</connect_id>
    <username>mahendran</username>
    <teamname>mahendran</teamname>
    <run>472</run>
  </user>
  <user>
    <user_id>6</user_id>
    <connect_id>515760568</connect_id>
    <username>gameboy123</username>
    <teamname>superstars</teamname>
    <run>414</run>
  </user>
</results>
