{"76":{"id":"76","player_name":"MS Dhoni","runs":"14","balls":"6","fours":"1","sixs":"1","wickets":"0","maiden":"0","overs":"0","wide":"0","no_balls":"0","rungiven":"0","caught":"0","stumped":"0","runout":"0","photo_url":"MDhoni1937123370.png","consfour":"0","conssix":"0","coc":{"batting":39,"battingbonus":0,"bowling":0,"fielding":0}},"80":{"id":"80","player_name":" R Jadeja","runs":"8","balls":"7","fours":"1","sixs":"0","wickets":"1","maiden":"0","overs":"6","wide":"0","no_balls":"0","rungiven":"16","caught":"0","stumped":"0","runout":"0","photo_url":"RJadeja638310382.png","consfour":"0","conssix":"0","coc":{"batting":13,"battingbonus":0,"bowling":10,"fielding":0}},"83":{"id":"83","player_name":" I Ahmed","runs":"0","balls":"0","fours":"0","sixs":"0","wickets":"0","maiden":"0","overs":"0","wide":"0","no_balls":"0","rungiven":"0","caught":"0","stumped":"3","runout":"0","photo_url":"IAhmed398775403.jpg","consfour":false,"conssix":false,"coc":{"batting":"0","battingbonus":0,"bowling":0,"fielding":45}},"86":{"id":"86","player_name":"M Hussey","runs":"7","balls":"5","fours":"0","sixs":"0","wickets":"1","maiden":"0","overs":"6","wide":"0","no_balls":"0","rungiven":"7","caught":"0","stumped":"0","runout":"1","photo_url":"MHussey152342021.png","consfour":"0","conssix":"0","coc":{"batting":17,"battingbonus":0,"bowling":35,"fielding":15}},"90":{"id":"90","player_name":" B Hilfenhaus","runs":"0","balls":"1","fours":"0","sixs":"0","wickets":"4","maiden":"0","overs":"6","wide":"0","no_balls":"0","rungiven":"10","caught":"0","stumped":"1","runout":"0","photo_url":"BHilfenhaus476000120.png","consfour":"0","conssix":"0","coc":{"batting":-10,"battingbonus":0,"bowling":100,"fielding":15}},"92":{"id":"92","player_name":" F Plessis","runs":"11","balls":"10","fours":"0","sixs":"0","wickets":"0","maiden":"0","overs":"0","wide":"0","no_balls":"0","rungiven":"0","caught":"0","stumped":"0","runout":"0","photo_url":"FPlessis1528798965.png","consfour":"0","conssix":"0","coc":{"batting":16,"battingbonus":0,"bowling":0,"fielding":0}},"93":{"id":"93","player_name":"D Bravo","runs":"8","balls":"4","fours":"2","sixs":"0","wickets":"1","maiden":"0","overs":"8","wide":"0","no_balls":"0","rungiven":"17","caught":"0","stumped":"0","runout":"0","photo_url":"DBravo760888076.png","consfour":"0","conssix":"0","coc":{"batting":33,"battingbonus":0,"bowling":10,"fielding":0}},"95":{"id":"95","player_name":"S Badrinath","runs":"12","balls":"12","fours":"1","sixs":"0","wickets":"0","maiden":"0","overs":"0","wide":"0","no_balls":"0","rungiven":"0","caught":"0","stumped":"0","runout":"0","photo_url":"SBadrinath1743410822.png","consfour":"0","conssix":"0","coc":{"batting":"12","battingbonus":0,"bowling":0,"fielding":0}},"96":{"id":"96","player_name":"R Ashwin","runs":"0","balls":"0","fours":"0","sixs":"0","wickets":"1","maiden":"0","overs":"6","wide":"1","no_balls":"0","rungiven":"10","caught":"0","stumped":"0","runout":"0","photo_url":"RAshwin986116568.png","consfour":false,"conssix":false,"coc":{"batting":"0","battingbonus":0,"bowling":8,"fielding":0}},"104":{"id":"104","player_name":"B Laughlin","runs":"1","balls":"2","fours":"0","sixs":"0","wickets":"0","maiden":"0","overs":"0","wide":"0","no_balls":"0","rungiven":"0","caught":"0","stumped":"0","runout":"0","photo_url":"BLaughlin1545909150.jpg","consfour":"0","conssix":"0","coc":{"batting":-9,"battingbonus":0,"bowling":0,"fielding":0}},"293":{"id":"293","player_name":" S Raina","runs":"1","balls":"1","fours":"0","sixs":"0","wickets":"0","maiden":"0","overs":"0","wide":"0","no_balls":"0","rungiven":"0","caught":"0","stumped":"0","runout":"0","photo_url":"SRaina185269420.png","consfour":"0","conssix":"0","coc":{"batting":"1","battingbonus":0,"bowling":0,"fielding":0}},"264":{"id":"264","player_name":" G Gambhir","runs":"4","balls":"3","fours":"0","sixs":"0","wickets":"0","maiden":"0","overs":"0","wide":"0","no_balls":"0","rungiven":"0","caught":"0","stumped":"1","runout":"0","photo_url":"GGambhir1465194615.png","consfour":"0","conssix":"0","coc":{"batting":14,"battingbonus":0,"bowling":0,"fielding":15}},"266":{"id":"266","player_name":"B  McCullum","runs":"0","balls":"1","fours":"0","sixs":"0","wickets":"0","maiden":"0","overs":"6","wide":"0","no_balls":"0","rungiven":"10","caught":"0","stumped":"0","runout":"1","photo_url":"BMcCullum947560797.png","consfour":"0","conssix":"0","coc":{"batting":-10,"battingbonus":0,"bowling":-15,"fielding":15}},"267":{"id":"267","player_name":" B Lee","runs":"22","balls":"9","fours":"2","sixs":"1","wickets":"2","maiden":"0","overs":"12","wide":"0","no_balls":"0","rungiven":"10","caught":"2","stumped":"2","runout":"0","photo_url":"BLee1317740702.png","consfour":"0","conssix":"0","coc":{"batting":47,"battingbonus":0,"bowling":65,"fielding":50}},"268":{"id":"268","player_name":" D Das","runs":"8","balls":"5","fours":"0","sixs":"0","wickets":"3","maiden":"0","overs":"8","wide":"1","no_balls":"0","rungiven":"7","caught":"0","stumped":"0","runout":"1","photo_url":"DDas241279608.png","consfour":"0","conssix":"0","coc":{"batting":23,"battingbonus":0,"bowling":103,"fielding":15}},"269":{"id":"269","player_name":"E Morgan","runs":"6","balls":"2","fours":"0","sixs":"1","wickets":"0","maiden":"0","overs":"0","wide":"0","no_balls":"0","rungiven":"0","caught":"0","stumped":"0","runout":"0","photo_url":"EMorgan516704693.png","consfour":"0","conssix":"0","coc":{"batting":31,"battingbonus":0,"bowling":0,"fielding":0}},"271":{"id":"271","player_name":"J Kallis","runs":"1","balls":"1","fours":"0","sixs":"0","wickets":"3","maiden":"0","overs":"18","wide":"0","no_balls":"0","rungiven":"29","caught":"0","stumped":"0","runout":"0","photo_url":"JKallis1228557274.png","consfour":"0","conssix":"0","coc":{"batting":"1","battingbonus":0,"bowling":80,"fielding":0}},"272":{"id":"272","player_name":"J Pattinson","runs":"0","balls":"0","fours":"0","sixs":"0","wickets":"0","maiden":"0","overs":"0","wide":"0","no_balls":"0","rungiven":"0","caught":"0","stumped":"1","runout":"0","photo_url":"JPattinson453757574.png","consfour":false,"conssix":false,"coc":{"batting":"0","battingbonus":0,"bowling":0,"fielding":15}},"273":{"id":"273","player_name":"L Balaji","runs":"13","balls":"4","fours":"1","sixs":"1","wickets":"0","maiden":"0","overs":"6","wide":"0","no_balls":"0","rungiven":"7","caught":"0","stumped":"0","runout":"0","photo_url":"LBalaji785594180.png","consfour":"0","conssix":"0","coc":{"batting":38,"battingbonus":0,"bowling":10,"fielding":0}},"274":{"id":"274","player_name":"L Shukla","runs":"5","balls":"5","fours":"1","sixs":"0","wickets":"0","maiden":"0","overs":"0","wide":"0","no_balls":"0","rungiven":"0","caught":"0","stumped":"0","runout":"0","photo_url":"LShukla365656013.png","consfour":"0","conssix":"0","coc":{"batting":"5","battingbonus":0,"bowling":0,"fielding":0}},"275":{"id":"275","player_name":"M Tiwary","runs":"0","balls":"1","fours":"0","sixs":"0","wickets":"0","maiden":"0","overs":"0","wide":"0","no_balls":"0","rungiven":"0","caught":"0","stumped":"0","runout":"0","photo_url":"MTiwary1990898350.png","consfour":"0","conssix":"0","coc":{"batting":-10,"battingbonus":0,"bowling":0,"fielding":0}},"276":{"id":"276","player_name":" M Bisla","runs":"0","balls":"1","fours":"0","sixs":"0","wickets":"0","maiden":"0","overs":"0","wide":"0","no_balls":"0","rungiven":"0","caught":"0","stumped":"0","runout":"0","photo_url":"MBisla1267501691.png","consfour":"0","conssix":"0","coc":{"batting":-10,"battingbonus":0,"bowling":0,"fielding":0}}}